ez_django_common/__init__.py
ez_django_common/choices.py
ez_django_common/custom_throttle.py
ez_django_common/models.py
ez_django_common/permissions.py
ez_django_common/responses.py
ez_django_common/storages.py
ez_django_common/admin/__init__.py
ez_django_common/admin/admin.py
ez_django_common/admin/inlines.py
ez_django_common/custom_responses/__init__.py
ez_django_common/custom_responses/enveloper.py
ez_django_common/custom_responses/exception.py
ez_django_common/custom_responses/jwt.py
ez_django_common/custom_responses/mixins.py
ez_django_common/custom_responses/pagination.py
ez_django_common/custom_responses/response.py
ez_django_common/custom_responses/viewsets.py
ez_django_common/migrations/__init__.py
ez_django_common/static/1284810432_3-70x70.png
ez_django_common/static/fonts/IRANYekanWebRegular.ttf
ez_django_common/templates/admin/base.html
ez_django_common/utils/__init__.py
ez_django_common/utils/loggers.py
ez_django_common/utils/sms.py
ez_django_common/utils/utils.py
EZDjangoCommon-1.0.0.dist-info/LICENSE
EZDjangoCommon-1.0.0.dist-info/METADATA
EZDjangoCommon-1.0.0.dist-info/WHEEL
EZDjangoCommon-1.0.0.dist-info/top_level.txt
EZDjangoCommon-1.0.0.dist-info/RECORD
