Metadata-Version: 2.1
Name: EZDjangoCommon
Version: 1.0.0
Summary: EZDjangoCommon
Home-page: https://github.com/ezhoosh/EZDjangoCommon
Download-URL: https://pypi.python.org/pypi/ez-django-common/
Author: ezhoosh
Author-email: ezhoosh@ezhoosh.com
License: MIT
Keywords: common
Platform: any
Classifier: Environment :: Web Environment
Classifier: Intended Audience :: Developers
Classifier: Operating System :: OS Independent
Classifier: Topic :: Software Development :: Libraries :: Application Frameworks
Classifier: Topic :: Software Development :: Libraries :: Python Modules
Classifier: Programming Language :: Python
Classifier: Programming Language :: Python :: 3.8
Classifier: Programming Language :: Python :: 3.9
Classifier: Programming Language :: Python :: 3.10
Classifier: Programming Language :: Python :: 3.11
Classifier: Framework :: Django
Classifier: Framework :: Django :: 2.2
Classifier: Framework :: Django :: 3.2
Classifier: Framework :: Django :: 4.2
Classifier: Framework :: Django :: 5.0
Requires-Python: >=3
License-File: LICENSE
Requires-Dist: django
Requires-Dist: django-unfold
Requires-Dist: django-tinymce
Requires-Dist: django-lifecycle
Requires-Dist: djangorestframework
Requires-Dist: loguru
Requires-Dist: kavenegar
Requires-Dist: drf-spectacular
Requires-Dist: django-image-uploader-widget
